{
  "TableName": "organizations",
  "KeySchema": [
    {
      "AttributeName": "ID",
      "KeyType": "HASH"
    }
  ],
  "AttributeDefinitions": [
    {
      "AttributeName": "ID",
      "AttributeType": "N"
    },
    {
      "AttributeName": "name",
      "AttributeType": "S"
    }
  ],
  "ProvisionedThroughput": {
    "ReadCapacityUnits": 5,
    "WriteCapacityUnits": 5
  },
  "GlobalSecondaryIndexes": [
    {
      "IndexName": "NameIndex",
      "KeySchema": [
        {
          "AttributeName": "name",
          "KeyType": "HASH"
        }
      ],
      "Projection": {
        "ProjectionType": "ALL"
      },
      "ProvisionedThroughput": {
        "ReadCapacityUnits": 5,
        "WriteCapacityUnits": 5
      }
    }
  ]
}
